cli.py
cosign.py
ctx.py
dockerutil.py
gitutil.py
gziputil.py
http_requests.py
ioutil.py
mailutil.py
makoutil.py
reutil.py
setup.py
signingserver.py
tarutil.py
util.py
version.py
ccc/__init__.py
ccc/alicloud.py
ccc/aws.py
ccc/cfg.py
ccc/clamav.py
ccc/concourse.py
ccc/delivery.py
ccc/elasticsearch.py
ccc/gcp.py
ccc/github.py
ccc/grafeas_model.py
ccc/oci.py
ccc/protecode.py
ccc/secrets_server.py
ccc/slack.py
cfg_mgmt/__init__.py
cfg_mgmt/alicloud.py
cfg_mgmt/aws.py
cfg_mgmt/azure.py
cfg_mgmt/btp_application_certificate.py
cfg_mgmt/btp_service_binding.py
cfg_mgmt/gcp.py
cfg_mgmt/github.py
cfg_mgmt/kubernetes.py
cfg_mgmt/metrics.py
cfg_mgmt/model.py
cfg_mgmt/reporting.py
cfg_mgmt/rotate.py
cfg_mgmt/util.py
checkmarx/__init__.py
checkmarx/client.py
checkmarx/model.py
checkmarx/project.py
checkmarx/tablefmt.py
checkmarx/util.py
ci/__init__.py
ci/log.py
ci/paths.py
ci/util.py
clamav/__init__.py
clamav/client.py
clamav/cnudie.py
clamav/model.py
clamav/report.py
clamav/routes.py
clamav/scan.py
clamav/util.py
cnudie/__init__.py
cnudie/access.py
cnudie/iter.py
cnudie/migrate.py
cnudie/purge.py
cnudie/retrieve.py
cnudie/upload.py
cnudie/util.py
cnudie/validate.py
concourse/__init__.py
concourse/enumerator.py
concourse/factory.py
concourse/paths.py
concourse/replicator.py
concourse/util.py
concourse/validator.py
concourse/client/__init__.py
concourse/client/api.py
concourse/client/model.py
concourse/client/routes.py
concourse/client/util.py
concourse/model/__init__.py
concourse/model/base.py
concourse/model/job.py
concourse/model/pipeline.py
concourse/model/resources.py
concourse/model/step.py
concourse/model/traits/__init__.py
concourse/model/traits/component_descriptor.py
concourse/model/traits/cronjob.py
concourse/model/traits/draft_release.py
concourse/model/traits/filter.py
concourse/model/traits/image_scan.py
concourse/model/traits/images.py
concourse/model/traits/meta.py
concourse/model/traits/notifications.py
concourse/model/traits/options.py
gardener_cicd_dso-1.2459.0.dist-info/LICENSE
gardener_cicd_dso-1.2459.0.dist-info/METADATA
gardener_cicd_dso-1.2459.0.dist-info/WHEEL
gardener_cicd_dso-1.2459.0.dist-info/top_level.txt
gardener_cicd_dso-1.2459.0.dist-info/RECORD
