Metadata-Version: 2.1
Name: gardener-cicd-dso
Version: 1.2459.0
Summary: Gardener CI/CD DevSecOps
Requires-Python: >=3.11
License-File: LICENSE
Requires-Dist: gardener-cicd-libs
Requires-Dist: gardener-cicd-cli
